quad/__init__.py
quad/asymmetric_local_collection.py
quad/asymmetric_local_collection_test.py
quad/vector_store.py
quad/benchmark/__init__.py
quad/benchmark/benchmark_generate.py
quad/benchmark/benchmark_test.py
quad/benchmark/circuits.py
quad/benchmark/scratch.py
quad/lsh/__init__.py
quad/lsh/l2_distance_hash.py
quad/lsh/meta_hash.py
quad/lsh/mips_hash.py
quad/lsh/raw_types.py
quad/lsh/state_vector_distance_hash.py
quad-0.1.0.dist-info/LICENSE.txt
quad-0.1.0.dist-info/METADATA
quad-0.1.0.dist-info/WHEEL
quad-0.1.0.dist-info/top_level.txt
quad-0.1.0.dist-info/RECORD
