Metadata-Version: 2.1
Name: quad
Version: 0.1.0
Summary: A database for storing and querying quantum state vectors.
Home-page: https://github.com/cduck/quantum-state-database
Author: Casey Duckering
License: UNKNOWN
Download-URL: https://github.com/cduck/quantum-state-database/archive/0.1.0.tar.gz
Keywords: quantum computing,databases,locality sensitive hashing
Platform: UNKNOWN
Classifier: License :: OSI Approved :: MIT License
Classifier: Development Status :: 3 - Alpha
Classifier: Programming Language :: Python :: 3
Classifier: Programming Language :: Python :: 3.7
Requires-Dist: numpy
Requires-Dist: cirq-unstable (==0.8.0.dev20200312000748)
Requires-Dist: zarr (~=2.4)
Requires-Dist: numcodecs (~=0.6.4)
Provides-Extra: dev
Requires-Dist: pytest ; extra == 'dev'
Requires-Dist: pytest-benchmark ; extra == 'dev'
